LICENSE
MANIFEST.in
README.rst
setup.py
tox.ini
tests/benchmark.py
tests/test_distribution.py
tests/test_implementation.py
tests/test_ketama_compatibility.py
uhashring/__init__.py
uhashring/monkey.py
uhashring/ring.py
uhashring/ring_ketama.py
uhashring/ring_meta.py
uhashring.egg-info/PKG-INFO
uhashring.egg-info/SOURCES.txt
uhashring.egg-info/dependency_links.txt
uhashring.egg-info/top_level.txt
uhashring.egg-info/zip-safe