Metadata-Version: 1.1
Name: uhashring
Version: 1.0
Summary: Full featured consistent hashing python library compatible with ketama.
Home-page: https://github.com/ultrabug/uhashring
Author: Ultrabug
Author-email: ultrabug@ultrabug.net
License: BSD
Download-URL: https://github.com/ultrabug/uhashring/tags
Platform: any
Classifier: License :: OSI Approved :: BSD License
Classifier: Operating System :: POSIX :: Linux
Classifier: Programming Language :: Python
Classifier: Programming Language :: Python :: 2.6
Classifier: Programming Language :: Python :: 2.7
Classifier: Programming Language :: Python :: 3
Classifier: Programming Language :: Python :: 3.2
Classifier: Programming Language :: Python :: 3.3
Classifier: Programming Language :: Python :: 3.4
Classifier: Programming Language :: Python :: 3.5
Classifier: Programming Language :: Python :: 3.6
Classifier: Topic :: Software Development :: Libraries :: Python Modules
